odoo/addons/account_move_substate/README.rst
odoo/addons/account_move_substate/__init__.py
odoo/addons/account_move_substate/__manifest__.py
odoo/addons/account_move_substate/data/account_move_substate_data.xml
odoo/addons/account_move_substate/data/account_move_substate_mail_template_data.xml
odoo/addons/account_move_substate/demo/account_move_substate_demo.xml
odoo/addons/account_move_substate/i18n/account_move_substate.pot
odoo/addons/account_move_substate/i18n/es.po
odoo/addons/account_move_substate/i18n/it.po
odoo/addons/account_move_substate/models/__init__.py
odoo/addons/account_move_substate/models/account_move.py
odoo/addons/account_move_substate/readme/CONTRIBUTORS.rst
odoo/addons/account_move_substate/readme/DESCRIPTION.rst
odoo/addons/account_move_substate/readme/USAGE.rst
odoo/addons/account_move_substate/static/description/icon.png
odoo/addons/account_move_substate/static/description/index.html
odoo/addons/account_move_substate/tests/__init__.py
odoo/addons/account_move_substate/tests/test_account_move_substate.py
odoo/addons/account_move_substate/views/account_move_views.xml
odoo_addon_account_move_substate-16.0.1.0.1.dist-info/METADATA
odoo_addon_account_move_substate-16.0.1.0.1.dist-info/WHEEL
odoo_addon_account_move_substate-16.0.1.0.1.dist-info/top_level.txt
odoo_addon_account_move_substate-16.0.1.0.1.dist-info/RECORD
